.bzrignore
.reahlproject
COPYING
LICENSE
reahl
setup.py
tox.ini
reahl/__init__.py
reahl/interfaces.py
reahl_interfaces.egg-info/PKG-INFO
reahl_interfaces.egg-info/SOURCES.txt
reahl_interfaces.egg-info/dependency_links.txt
reahl_interfaces.egg-info/entry_points.txt
reahl_interfaces.egg-info/namespace_packages.txt
reahl_interfaces.egg-info/top_level.txt