Metadata-Version: 1.0
Name: reahl-interfaces
Version: 3.1.0
Summary: Python abstract classes for important Reahl interfaces.
Home-page: http://www.reahl.org
Author: Iwan Vosloo
Author-email: iwan@reahl.org
License: UNKNOWN
Platform: UNKNOWN
